{
    "_links": {
        "self": {
            "href": "http:\/\/default\/sites\/default\/files\/2020-01\/Spring-forest-in-fog.jpg"
        },
        "type": {
            "href": "http:\/\/drupal.org\/rest\/type\/file\/file"
        },
        "http:\/\/drupal.org\/rest\/relation\/file\/file\/uid": [
            {
                "href": "http:\/\/default\/user\/1?_format=hal_json"
            }
        ]
    },
    "fid": [
        {
            "value": 7
        }
    ],
    "uuid": [
        {
            "value": "53279e65-922b-446a-a60d-41e9b3a976c3"
        }
    ],
    "langcode": [
        {
            "value": "en"
        }
    ],
    "_embedded": {
        "http:\/\/drupal.org\/rest\/relation\/file\/file\/uid": [
            {
                "_links": {
                    "self": {
                        "href": "http:\/\/default\/user\/1?_format=hal_json"
                    },
                    "type": {
                        "href": "http:\/\/drupal.org\/rest\/type\/user\/user"
                    }
                },
                "uuid": [
                    {
                        "value": "3e8ba544-2bae-4989-aa6f-40cb4fb52716"
                    }
                ]
            }
        ]
    },
    "filename": [
        {
            "value": "Spring-forest-in-fog.jpg"
        }
    ],
    "uri": [
        {
            "value": "public:\/\/2020-01\/Spring-forest-in-fog.jpg",
            "url": "\/sites\/default\/files\/2020-01\/Spring-forest-in-fog.jpg"
        }
    ],
    "filemime": [
        {
            "value": "image\/jpeg"
        }
    ],
    "filesize": [
        {
            "value": 13924288
        }
    ],
    "status": [
        {
            "value": true
        }
    ],
    "created": [
        {
            "value": "2020-01-16T22:54:46+00:00",
            "format": "Y-m-d\\TH:i:sP"
        }
    ],
    "changed": [
        {
            "value": "2020-01-16T22:54:50+00:00",
            "format": "Y-m-d\\TH:i:sP"
        }
    ]
}